test/__init__.py
test/test_default_api.py
test/test_wv_table.py
wellview_api/__init__.py
wellview_api/api_client.py
wellview_api/configuration.py
wellview_api/rest.py
wellview_api/api/__init__.py
wellview_api/api/default_api.py
wellview_api/models/__init__.py
wellview_api/models/wv_table.py
wellview_api-1.0.0.dist-info/METADATA
wellview_api-1.0.0.dist-info/WHEEL
wellview_api-1.0.0.dist-info/top_level.txt
wellview_api-1.0.0.dist-info/RECORD
