Metadata-Version: 2.1
Name: wellview-api
Version: 1.0.0
Summary: WellViewAPI
Home-page: 
Author-email: 
License: UNKNOWN
Keywords: Swagger,WellViewAPI
Platform: UNKNOWN
Requires-Dist: urllib3 (>=1.15)
Requires-Dist: six (>=1.10)
Requires-Dist: certifi
Requires-Dist: python-dateutil
